taboo/__init__.py
taboo/attacker.py
taboo/checker.py
taboo/defender.py
taboo/formatter.py
taboo/judger.py
taboo/ruler.py
taboo/util.py
taboo/attacker/__init__.py
taboo/attacker/attacker.py
taboo/checker/__init__.py
taboo/checker/chinese.py
taboo/checker/english.py
taboo/defender/__init__.py
taboo/defender/defender.py
taboo/formatter/__init__.py
taboo/formatter/stupid.py
taboo/judger/__init__.py
taboo/judger/judger.py
taboo/ruler/__init__.py
taboo/ruler/stupid.py
taboo-0.8.8.dist-info/LICENSE
taboo-0.8.8.dist-info/METADATA
taboo-0.8.8.dist-info/WHEEL
taboo-0.8.8.dist-info/top_level.txt
taboo-0.8.8.dist-info/RECORD
